[
  {
    "line": 10,
    "elements": [
      {
        "line": 30,
        "name": "Filling Grid Harmonization form for Demand response program available and participation",
        "description": "",
        "id": "entering-data-to-grid-harmonization-form---leed-v4.1-o+m:-eb;filling-grid-harmonization-form-for-demand-response-program-available-and-participation;;2",
        "type": "scenario",
        "keyword": "Scenario Outline",
        "steps": [
          {
            "result": {
              "duration": 144886544214,
              "status": "passed"
            },
            "line": 14,
            "name": "User clicks on project BDD6 TestProject",
            "match": {
              "arguments": [
                {
                  "val": "BDD6 TestProject",
                  "offset": 23
                }
              ],
              "location": "FundamentalRefregrantMgmt.user_clicks_on_Project(String)"
            },
            "keyword": "Given "
          },
          {
            "result": {
              "duration": 2879726023,
              "status": "passed"
            },
            "line": 15,
            "name": "User navigates to the credits page of the project",
            "match": {
              "location": "FundamentalRefregrantMgmt.user_navigates_to_the_credits_page_of_the_project()"
            },
            "keyword": "And "
          },
          {
            "result": {
              "duration": 32429923107,
              "status": "passed"
            },
            "line": 16,
            "name": "User should be on form Grid Harmonization-demandResProgramAvail rating O+M:EB",
            "match": {
              "arguments": [
                {
                  "val": "Grid Harmonization-demandResProgramAvail",
                  "offset": 23
                },
                {
                  "val": "O+M:EB",
                  "offset": 71
                }
              ],
              "location": "FundamentalRefregrantMgmt.user_should_be_on_FRM_form(String,String)"
            },
            "keyword": "And "
          },
          {
            "result": {
              "duration": 8335503278,
              "status": "passed"
            },
            "line": 17,
            "name": "User will select the Radio Button",
            "match": {
              "location": "FundamentalRefregrantMgmt.User_will_select_the_Radio_Button()"
            },
            "keyword": "When "
          },
          {
            "result": {
              "duration": 855488623,
              "status": "passed"
            },
            "line": 18,
            "name": "User checks the checkbox option",
            "match": {
              "location": "FundamentalRefregrantMgmt.user_checks_the_checkbox_option()"
            },
            "keyword": "And "
          },
          {
            "result": {
              "duration": 5701297727,
              "status": "passed"
            },
            "line": 19,
            "name": "User enters data to text box with number",
            "match": {
              "location": "FundamentalRefregrantMgmt.user_enters_data_to_text_box_with_number()"
            },
            "keyword": "And "
          },
          {
            "result": {
              "duration": 43867221767,
              "status": "passed"
            },
            "line": 20,
            "name": "User uploads files to Add file button",
            "match": {
              "location": "FundamentalRefregrantMgmt.user_uploads_files_to_Add_file_button()"
            },
            "keyword": "And "
          },
          {
            "result": {
              "duration": 3960285454,
              "status": "passed"
            },
            "line": 21,
            "name": "User Enters data to Narrative field",
            "match": {
              "location": "FundamentalRefregrantMgmt.user_enters_data_to_Narrative_field()"
            },
            "keyword": "And "
          },
          {
            "result": {
              "duration": 318264816590,
              "status": "passed"
            },
            "line": 22,
            "name": "User downloads the uploaded files",
            "match": {
              "location": "FundamentalRefregrantMgmt.user_downloads_the_uploaded_files()"
            },
            "keyword": "And "
          },
          {
            "result": {
              "duration": 133300802752,
              "status": "passed"
            },
            "line": 23,
            "name": "User deletes the uploaded files",
            "match": {
              "location": "FundamentalRefregrantMgmt.user_deletes_the_uploaded_files()"
            },
            "keyword": "And "
          },
          {
            "result": {
              "duration": 5558116164,
              "status": "passed"
            },
            "line": 24,
            "name": "User clicks on Save button",
            "match": {
              "location": "FundamentalRefregrantMgmt.User_clicks_on_Save_button()"
            },
            "keyword": "And "
          },
          {
            "result": {
              "duration": 8326041081,
              "status": "passed"
            },
            "line": 25,
            "name": "User can able to see the form got saved",
            "match": {
              "location": "FundamentalRefregrantMgmt.user_can_able_to_see_the_form_got_saved()"
            },
            "keyword": "Then "
          },
          {
            "result": {
              "duration": 58468298023,
              "status": "passed"
            },
            "line": 26,
            "name": "User clicks the Complete icon to set status to Ready for Review",
            "match": {
              "location": "FundamentalRefregrantMgmt.User_clicks_the_Complete_icon_to_set_status_to_Ready_for_Review()"
            },
            "keyword": "And "
          }
        ],
        "tags": [
          {
            "name": "@SmokeTest"
          }
        ]
      },
      {
        "line": 50,
        "name": "Filling Grid Harmonization form for Demand response capable building",
        "description": "",
        "id": "entering-data-to-grid-harmonization-form---leed-v4.1-o+m:-eb;filling-grid-harmonization-form-for-demand-response-capable-building;;2",
        "type": "scenario",
        "keyword": "Scenario Outline",
        "steps": [
          {
            "result": {
              "duration": 130668230015,
              "status": "passed"
            },
            "line": 34,
            "name": "User clicks on project BDD6 TestProject",
            "match": {
              "arguments": [
                {
                  "val": "BDD6 TestProject",
                  "offset": 23
                }
              ],
              "location": "FundamentalRefregrantMgmt.user_clicks_on_Project(String)"
            },
            "keyword": "Given "
          },
          {
            "result": {
              "duration": 3919450386,
              "status": "passed"
            },
            "line": 35,
            "name": "User navigates to the credits page of the project",
            "match": {
              "location": "FundamentalRefregrantMgmt.user_navigates_to_the_credits_page_of_the_project()"
            },
            "keyword": "And "
          },
          {
            "result": {
              "duration": 23059057966,
              "status": "passed"
            },
            "line": 36,
            "name": "User should be on form Grid Harmonization-demandResCapableBuilding rating O+M:EB",
            "match": {
              "arguments": [
                {
                  "val": "Grid Harmonization-demandResCapableBuilding",
                  "offset": 23
                },
                {
                  "val": "O+M:EB",
                  "offset": 74
                }
              ],
              "location": "FundamentalRefregrantMgmt.user_should_be_on_FRM_form(String,String)"
            },
            "keyword": "And "
          },
          {
            "result": {
              "duration": 3457074046,
              "status": "passed"
            },
            "line": 37,
            "name": "User will select the Radio Button",
            "match": {
              "location": "FundamentalRefregrantMgmt.User_will_select_the_Radio_Button()"
            },
            "keyword": "When "
          },
          {
            "result": {
              "duration": 4726942140,
              "status": "passed"
            },
            "line": 38,
            "name": "User checks the checkbox option",
            "match": {
              "location": "FundamentalRefregrantMgmt.user_checks_the_checkbox_option()"
            },
            "keyword": "And "
          },
          {
            "result": {
              "duration": 2957620474,
              "status": "passed"
            },
            "line": 39,
            "name": "User enters data to text box with number",
            "match": {
              "location": "FundamentalRefregrantMgmt.user_enters_data_to_text_box_with_number()"
            },
            "keyword": "And "
          },
          {
            "result": {
              "duration": 1878276170,
              "status": "passed"
            },
            "line": 40,
            "name": "User uploads files to Add file button",
            "match": {
              "location": "FundamentalRefregrantMgmt.user_uploads_files_to_Add_file_button()"
            },
            "keyword": "And "
          },
          {
            "result": {
              "duration": 7606444594,
              "status": "passed"
            },
            "line": 41,
            "name": "User Enters data to Narrative field",
            "match": {
              "location": "FundamentalRefregrantMgmt.user_enters_data_to_Narrative_field()"
            },
            "keyword": "And "
          },
          {
            "result": {
              "duration": 3149506207,
              "status": "passed"
            },
            "line": 42,
            "name": "User downloads the uploaded files",
            "match": {
              "location": "FundamentalRefregrantMgmt.user_downloads_the_uploaded_files()"
            },
            "keyword": "And "
          },
          {
            "result": {
              "duration": 3126769979,
              "status": "passed"
            },
            "line": 43,
            "name": "User deletes the uploaded files",
            "match": {
              "location": "FundamentalRefregrantMgmt.user_deletes_the_uploaded_files()"
            },
            "keyword": "And "
          },
          {
            "result": {
              "duration": 2916538631,
              "status": "passed"
            },
            "line": 44,
            "name": "User clicks on Save button",
            "match": {
              "location": "FundamentalRefregrantMgmt.User_clicks_on_Save_button()"
            },
            "keyword": "And "
          },
          {
            "result": {
              "duration": 2520644896,
              "status": "passed"
            },
            "line": 45,
            "name": "User can able to see the form got saved",
            "match": {
              "location": "FundamentalRefregrantMgmt.user_can_able_to_see_the_form_got_saved()"
            },
            "keyword": "Then "
          },
          {
            "result": {
              "duration": 61473571757,
              "status": "passed"
            },
            "line": 46,
            "name": "User clicks the Complete icon to set status to Ready for Review",
            "match": {
              "location": "FundamentalRefregrantMgmt.User_clicks_the_Complete_icon_to_set_status_to_Ready_for_Review()"
            },
            "keyword": "And "
          }
        ],
        "tags": [
          {
            "name": "@SmokeTest"
          }
        ]
      },
      {
        "line": 70,
        "name": "Filling Grid Harmonization form for Permanent load shifting technologies",
        "description": "",
        "id": "entering-data-to-grid-harmonization-form---leed-v4.1-o+m:-eb;filling-grid-harmonization-form-for-permanent-load-shifting-technologies;;2",
        "type": "scenario",
        "keyword": "Scenario Outline",
        "steps": [
          {
            "result": {
              "duration": 94192114657,
              "status": "passed"
            },
            "line": 54,
            "name": "User clicks on project BDD6 TestProject",
            "match": {
              "arguments": [
                {
                  "val": "BDD6 TestProject",
                  "offset": 23
                }
              ],
              "location": "FundamentalRefregrantMgmt.user_clicks_on_Project(String)"
            },
            "keyword": "Given "
          },
          {
            "result": {
              "duration": 4479225245,
              "status": "passed"
            },
            "line": 55,
            "name": "User navigates to the credits page of the project",
            "match": {
              "location": "FundamentalRefregrantMgmt.user_navigates_to_the_credits_page_of_the_project()"
            },
            "keyword": "And "
          },
          {
            "result": {
              "duration": 44632890464,
              "status": "passed"
            },
            "line": 56,
            "name": "User should be on form Grid Harmonization-permLoadShiftTechnologies rating O+M:EB",
            "match": {
              "arguments": [
                {
                  "val": "Grid Harmonization-permLoadShiftTechnologies",
                  "offset": 23
                },
                {
                  "val": "O+M:EB",
                  "offset": 75
                }
              ],
              "location": "FundamentalRefregrantMgmt.user_should_be_on_FRM_form(String,String)"
            },
            "keyword": "And "
          },
          {
            "result": {
              "duration": 19908791803,
              "status": "passed"
            },
            "line": 57,
            "name": "User will select the Radio Button",
            "match": {
              "location": "FundamentalRefregrantMgmt.User_will_select_the_Radio_Button()"
            },
            "keyword": "When "
          },
          {
            "result": {
              "duration": 3168479243,
              "status": "passed"
            },
            "line": 58,
            "name": "User checks the checkbox option",
            "match": {
              "location": "FundamentalRefregrantMgmt.user_checks_the_checkbox_option()"
            },
            "keyword": "And "
          },
          {
            "result": {
              "duration": 7182680126,
              "status": "passed"
            },
            "line": 59,
            "name": "User enters data to text box with number",
            "match": {
              "location": "FundamentalRefregrantMgmt.user_enters_data_to_text_box_with_number()"
            },
            "keyword": "And "
          },
          {
            "result": {
              "duration": 44569142900,
              "status": "passed"
            },
            "line": 60,
            "name": "User uploads files to Add file button",
            "match": {
              "location": "FundamentalRefregrantMgmt.user_uploads_files_to_Add_file_button()"
            },
            "keyword": "And "
          },
          {
            "result": {
              "duration": 4943148274,
              "status": "passed"
            },
            "line": 61,
            "name": "User Enters data to Narrative field",
            "match": {
              "location": "FundamentalRefregrantMgmt.user_enters_data_to_Narrative_field()"
            },
            "keyword": "And "
          },
          {
            "result": {
              "duration": 413817575126,
              "status": "passed"
            },
            "line": 62,
            "name": "User downloads the uploaded files",
            "match": {
              "location": "FundamentalRefregrantMgmt.user_downloads_the_uploaded_files()"
            },
            "keyword": "And "
          },
          {
            "result": {
              "duration": 68742583951,
              "status": "passed"
            },
            "line": 63,
            "name": "User deletes the uploaded files",
            "match": {
              "location": "FundamentalRefregrantMgmt.user_deletes_the_uploaded_files()"
            },
            "keyword": "And "
          },
          {
            "result": {
              "duration": 5073576130,
              "status": "passed"
            },
            "line": 64,
            "name": "User clicks on Save button",
            "match": {
              "location": "FundamentalRefregrantMgmt.User_clicks_on_Save_button()"
            },
            "keyword": "And "
          },
          {
            "result": {
              "duration": 7766893642,
              "status": "passed"
            },
            "line": 65,
            "name": "User can able to see the form got saved",
            "match": {
              "location": "FundamentalRefregrantMgmt.user_can_able_to_see_the_form_got_saved()"
            },
            "keyword": "Then "
          },
          {
            "result": {
              "duration": 42393324251,
              "status": "passed"
            },
            "line": 66,
            "name": "User clicks the Complete icon to set status to Ready for Review",
            "match": {
              "location": "FundamentalRefregrantMgmt.User_clicks_the_Complete_icon_to_set_status_to_Ready_for_Review()"
            },
            "keyword": "And "
          }
        ],
        "tags": [
          {
            "name": "@SmokeTest"
          }
        ]
      },
      {
        "line": 96,
        "name": "Checking Auto Save functionality in Grid Harmonization form for Demand response program available and participation",
        "description": "",
        "id": "entering-data-to-grid-harmonization-form---leed-v4.1-o+m:-eb;checking-auto-save-functionality-in-grid-harmonization-form-for-demand-response-program-available-and-participation;;2",
        "type": "scenario",
        "keyword": "Scenario Outline",
        "steps": [
          {
            "result": {
              "duration": 141260741474,
              "status": "passed"
            },
            "line": 74,
            "name": "User clicks on project BDD6 TestProject",
            "match": {
              "arguments": [
                {
                  "val": "BDD6 TestProject",
                  "offset": 23
                }
              ],
              "location": "FundamentalRefregrantMgmt.user_clicks_on_Project(String)"
            },
            "keyword": "Given "
          },
          {
            "result": {
              "duration": 4293021116,
              "status": "passed"
            },
            "line": 75,
            "name": "User navigates to the credits page of the project",
            "match": {
              "location": "FundamentalRefregrantMgmt.user_navigates_to_the_credits_page_of_the_project()"
            },
            "keyword": "And "
          },
          {
            "result": {
              "duration": 5250459968,
              "status": "passed"
            },
            "line": 76,
            "name": "User should be on form Grid Harmonization-demandResCapableBuilding rating O+M:EB    When User will select the Radio Button",
            "match": {
              "arguments": [
                {
                  "val": "Grid Harmonization-demandResCapableBuilding",
                  "offset": 23
                },
                {
                  "val": "O+M:EB    When User will select the Radio Button",
                  "offset": 74
                }
              ],
              "location": "FundamentalRefregrantMgmt.user_should_be_on_FRM_form(String,String)"
            },
            "keyword": "And "
          },
          {
            "result": {
              "error_message": "java.lang.NullPointerException: Cannot invoke method log() on null object\r\n\tat org.codehaus.groovy.runtime.NullObject.invokeMethod(NullObject.java:91)\r\n\tat org.codehaus.groovy.runtime.callsite.PogoMetaClassSite.call(PogoMetaClassSite.java:48)\r\n\tat org.codehaus.groovy.runtime.callsite.CallSiteArray.defaultCall(CallSiteArray.java:48)\r\n\tat org.codehaus.groovy.runtime.callsite.NullCallSite.call(NullCallSite.java:35)\r\n\tat org.codehaus.groovy.runtime.callsite.CallSiteArray.defaultCall(CallSiteArray.java:48)\r\n\tat org.codehaus.groovy.runtime.callsite.PogoMetaClassSite.call(PogoMetaClassSite.java:57)\r\n\tat org.codehaus.groovy.runtime.callsite.AbstractCallSite.call(AbstractCallSite.java:133)\r\n\tat AutoSaveStepDef.user_enters_data_to_Narrative_field(AutoSaveStepDef.groovy:206)\r\n\tat ✽.User Enters data to Narrative field to check auto save on form Grid Harmonization-demandResCapableBuilding rating O+M:EB(Include/features/ScoreCard/Grid Harmonization.feature:77)\r\n",
              "duration": 5199483069,
              "status": "failed"
            },
            "line": 77,
            "name": "User Enters data to Narrative field to check auto save on form Grid Harmonization-demandResCapableBuilding rating O+M:EB",
            "match": {
              "arguments": [
                {
                  "val": "Grid Harmonization-demandResCapableBuilding",
                  "offset": 63
                },
                {
                  "val": "O+M:EB",
                  "offset": 114
                }
              ],
              "location": "AutoSaveStepDef.user_enters_data_to_Narrative_field(String,String)"
            },
            "keyword": "And "
          },
          {
            "result": {
              "status": "skipped"
            },
            "line": 78,
            "name": "User uploads files to Add file button to check auto save on form Grid Harmonization-demandResCapableBuilding rating O+M:EB",
            "match": {
              "arguments": [
                {
                  "val": "Grid Harmonization-demandResCapableBuilding",
                  "offset": 65
                },
                {
                  "val": "O+M:EB",
                  "offset": 116
                }
              ],
              "location": "AutoSaveStepDef.user_uploads_files_to_Add_file_button(String,String)"
            },
            "keyword": "And "
          },
          {
            "result": {
              "status": "skipped"
            },
            "line": 79,
            "name": "User verifies form not saved as draft",
            "match": {
              "location": "AutoSaveStepDef.user_verifies_form_not_saved_as_draft()"
            },
            "keyword": "And "
          },
          {
            "result": {
              "status": "skipped"
            },
            "line": 80,
            "name": "User Enters data to Narrative field to check auto save on form Grid Harmonization-demandResCapableBuilding rating O+M:EB",
            "match": {
              "arguments": [
                {
                  "val": "Grid Harmonization-demandResCapableBuilding",
                  "offset": 63
                },
                {
                  "val": "O+M:EB",
                  "offset": 114
                }
              ],
              "location": "AutoSaveStepDef.user_enters_data_to_Narrative_field(String,String)"
            },
            "keyword": "And "
          },
          {
            "result": {
              "status": "skipped"
            },
            "line": 81,
            "name": "User verifies warning message of form saved as draft",
            "match": {
              "location": "AutoSaveStepDef.user_verifies_warning_message_of_form_saved_as_draft()"
            },
            "keyword": "And "
          },
          {
            "result": {
              "status": "skipped"
            },
            "line": 82,
            "name": "User checks form saved as draft",
            "match": {
              "location": "AutoSaveStepDef.user_checks_autosave()"
            },
            "keyword": "And "
          },
          {
            "result": {
              "status": "skipped"
            },
            "line": 83,
            "name": "User deletes the uploaded files",
            "match": {
              "location": "FundamentalRefregrantMgmt.user_deletes_the_uploaded_files()"
            },
            "keyword": "And "
          },
          {
            "result": {
              "status": "skipped"
            },
            "line": 84,
            "name": "User clears the draft",
            "match": {
              "location": "AutoSaveStepDef.user_clears_draft()"
            },
            "keyword": "And "
          },
          {
            "result": {
              "status": "skipped"
            },
            "line": 85,
            "name": "User Enters data to Narrative field after clear draft",
            "match": {
              "location": "AutoSaveStepDef.user_enters_data_to_Narrative_field_after_clear_draft()"
            },
            "keyword": "And "
          },
          {
            "result": {
              "status": "skipped"
            },
            "line": 86,
            "name": "User clicks on Save button",
            "match": {
              "location": "FundamentalRefregrantMgmt.User_clicks_on_Save_button()"
            },
            "keyword": "And "
          },
          {
            "result": {
              "status": "skipped"
            },
            "line": 87,
            "name": "User can able to see the form got saved",
            "match": {
              "location": "FundamentalRefregrantMgmt.user_can_able_to_see_the_form_got_saved()"
            },
            "keyword": "Then "
          },
          {
            "result": {
              "status": "skipped"
            },
            "line": 88,
            "name": "User verifies the revision icon present after saving the form",
            "match": {
              "location": "AutoSaveStepDef.user_verifies_the_revision_icon_present_after_saving_the_form()"
            },
            "keyword": "And "
          },
          {
            "result": {
              "status": "skipped"
            },
            "line": 89,
            "name": "User dowloads the form as pdf",
            "match": {
              "location": "AutoSaveStepDef.user_verifies_the_PDF()"
            },
            "keyword": "And "
          },
          {
            "result": {
              "status": "skipped"
            },
            "line": 90,
            "name": "User verifies the narrative",
            "match": {
              "location": "AutoSaveStepDef.user_verifies_the_narraive()"
            },
            "keyword": "And "
          },
          {
            "result": {
              "status": "skipped"
            },
            "line": 91,
            "name": "User verifies text with pdf",
            "match": {
              "location": "AutoSaveStepDef.user_verifies_text_with_pdf()"
            },
            "keyword": "And "
          },
          {
            "result": {
              "status": "skipped"
            },
            "line": 92,
            "name": "User deletes the downloaded pdf file",
            "match": {
              "location": "AutoSaveStepDef.user_deletes_the_downloaded_files()"
            },
            "keyword": "And "
          }
        ],
        "tags": [
          {
            "name": "@RegressionTest"
          }
        ]
      },
      {
        "line": 123,
        "name": "Checking Auto Save functionality in Grid Harmonization form for Permanent load shifting technologies",
        "description": "",
        "id": "entering-data-to-grid-harmonization-form---leed-v4.1-o+m:-eb;checking-auto-save-functionality-in-grid-harmonization-form-for-permanent-load-shifting-technologies;;2",
        "type": "scenario",
        "keyword": "Scenario Outline",
        "steps": [
          {
            "result": {
              "duration": 125598039999,
              "status": "passed"
            },
            "line": 100,
            "name": "User clicks on project BDD6 TestProject",
            "match": {
              "arguments": [
                {
                  "val": "BDD6 TestProject",
                  "offset": 23
                }
              ],
              "location": "FundamentalRefregrantMgmt.user_clicks_on_Project(String)"
            },
            "keyword": "Given "
          },
          {
            "result": {
              "duration": 3550824506,
              "status": "passed"
            },
            "line": 101,
            "name": "User navigates to the credits page of the project",
            "match": {
              "location": "FundamentalRefregrantMgmt.user_navigates_to_the_credits_page_of_the_project()"
            },
            "keyword": "And "
          },
          {
            "result": {
              "duration": 12382505911,
              "status": "passed"
            },
            "line": 102,
            "name": "User should be on form Grid Harmonization-permLoadShiftTechnologies rating O+M:EB",
            "match": {
              "arguments": [
                {
                  "val": "Grid Harmonization-permLoadShiftTechnologies",
                  "offset": 23
                },
                {
                  "val": "O+M:EB",
                  "offset": 75
                }
              ],
              "location": "FundamentalRefregrantMgmt.user_should_be_on_FRM_form(String,String)"
            },
            "keyword": "And "
          },
          {
            "result": {
              "duration": 3670308182,
              "status": "passed"
            },
            "line": 103,
            "name": "User will select the Radio Button",
            "match": {
              "location": "FundamentalRefregrantMgmt.User_will_select_the_Radio_Button()"
            },
            "keyword": "When "
          },
          {
            "result": {
              "error_message": "java.lang.NullPointerException: Cannot invoke method log() on null object\r\n\tat org.codehaus.groovy.runtime.NullObject.invokeMethod(NullObject.java:91)\r\n\tat org.codehaus.groovy.runtime.callsite.PogoMetaClassSite.call(PogoMetaClassSite.java:48)\r\n\tat org.codehaus.groovy.runtime.callsite.CallSiteArray.defaultCall(CallSiteArray.java:48)\r\n\tat org.codehaus.groovy.runtime.callsite.NullCallSite.call(NullCallSite.java:35)\r\n\tat org.codehaus.groovy.runtime.callsite.CallSiteArray.defaultCall(CallSiteArray.java:48)\r\n\tat org.codehaus.groovy.runtime.callsite.PogoMetaClassSite.call(PogoMetaClassSite.java:57)\r\n\tat org.codehaus.groovy.runtime.callsite.AbstractCallSite.call(AbstractCallSite.java:133)\r\n\tat AutoSaveStepDef.user_enters_data_to_Narrative_field(AutoSaveStepDef.groovy:206)\r\n\tat ✽.User Enters data to Narrative field to check auto save on form Grid Harmonization-permLoadShiftTechnologies rating O+M:EB(Include/features/ScoreCard/Grid Harmonization.feature:104)\r\n",
              "duration": 4555394957,
              "status": "failed"
            },
            "line": 104,
            "name": "User Enters data to Narrative field to check auto save on form Grid Harmonization-permLoadShiftTechnologies rating O+M:EB",
            "match": {
              "arguments": [
                {
                  "val": "Grid Harmonization-permLoadShiftTechnologies",
                  "offset": 63
                },
                {
                  "val": "O+M:EB",
                  "offset": 115
                }
              ],
              "location": "AutoSaveStepDef.user_enters_data_to_Narrative_field(String,String)"
            },
            "keyword": "And "
          },
          {
            "result": {
              "status": "skipped"
            },
            "line": 105,
            "name": "User uploads files to Add file button to check auto save on form Grid Harmonization-permLoadShiftTechnologies rating O+M:EB",
            "match": {
              "arguments": [
                {
                  "val": "Grid Harmonization-permLoadShiftTechnologies",
                  "offset": 65
                },
                {
                  "val": "O+M:EB",
                  "offset": 117
                }
              ],
              "location": "AutoSaveStepDef.user_uploads_files_to_Add_file_button(String,String)"
            },
            "keyword": "And "
          },
          {
            "result": {
              "status": "skipped"
            },
            "line": 106,
            "name": "User verifies form not saved as draft",
            "match": {
              "location": "AutoSaveStepDef.user_verifies_form_not_saved_as_draft()"
            },
            "keyword": "And "
          },
          {
            "result": {
              "status": "skipped"
            },
            "line": 107,
            "name": "User Enters data to Narrative field to check auto save on form Grid Harmonization-permLoadShiftTechnologies rating O+M:EB",
            "match": {
              "arguments": [
                {
                  "val": "Grid Harmonization-permLoadShiftTechnologies",
                  "offset": 63
                },
                {
                  "val": "O+M:EB",
                  "offset": 115
                }
              ],
              "location": "AutoSaveStepDef.user_enters_data_to_Narrative_field(String,String)"
            },
            "keyword": "And "
          },
          {
            "result": {
              "status": "skipped"
            },
            "line": 108,
            "name": "User verifies warning message of form saved as draft",
            "match": {
              "location": "AutoSaveStepDef.user_verifies_warning_message_of_form_saved_as_draft()"
            },
            "keyword": "And "
          },
          {
            "result": {
              "status": "skipped"
            },
            "line": 109,
            "name": "User checks form saved as draft",
            "match": {
              "location": "AutoSaveStepDef.user_checks_autosave()"
            },
            "keyword": "And "
          },
          {
            "result": {
              "status": "skipped"
            },
            "line": 110,
            "name": "User deletes the uploaded files",
            "match": {
              "location": "FundamentalRefregrantMgmt.user_deletes_the_uploaded_files()"
            },
            "keyword": "And "
          },
          {
            "result": {
              "status": "skipped"
            },
            "line": 111,
            "name": "User clears the draft",
            "match": {
              "location": "AutoSaveStepDef.user_clears_draft()"
            },
            "keyword": "And "
          },
          {
            "result": {
              "status": "skipped"
            },
            "line": 112,
            "name": "User Enters data to Narrative field after clear draft",
            "match": {
              "location": "AutoSaveStepDef.user_enters_data_to_Narrative_field_after_clear_draft()"
            },
            "keyword": "And "
          },
          {
            "result": {
              "status": "skipped"
            },
            "line": 113,
            "name": "User clicks on Save button",
            "match": {
              "location": "FundamentalRefregrantMgmt.User_clicks_on_Save_button()"
            },
            "keyword": "And "
          },
          {
            "result": {
              "status": "skipped"
            },
            "line": 114,
            "name": "User can able to see the form got saved",
            "match": {
              "location": "FundamentalRefregrantMgmt.user_can_able_to_see_the_form_got_saved()"
            },
            "keyword": "Then "
          },
          {
            "result": {
              "status": "skipped"
            },
            "line": 115,
            "name": "User verifies the revision icon present after saving the form",
            "match": {
              "location": "AutoSaveStepDef.user_verifies_the_revision_icon_present_after_saving_the_form()"
            },
            "keyword": "And "
          },
          {
            "result": {
              "status": "skipped"
            },
            "line": 116,
            "name": "User dowloads the form as pdf",
            "match": {
              "location": "AutoSaveStepDef.user_verifies_the_PDF()"
            },
            "keyword": "And "
          },
          {
            "result": {
              "status": "skipped"
            },
            "line": 117,
            "name": "User verifies the narrative",
            "match": {
              "location": "AutoSaveStepDef.user_verifies_the_narraive()"
            },
            "keyword": "And "
          },
          {
            "result": {
              "status": "skipped"
            },
            "line": 118,
            "name": "User verifies text with pdf",
            "match": {
              "location": "AutoSaveStepDef.user_verifies_text_with_pdf()"
            },
            "keyword": "And "
          },
          {
            "result": {
              "status": "skipped"
            },
            "line": 119,
            "name": "User deletes the downloaded pdf file",
            "match": {
              "location": "AutoSaveStepDef.user_deletes_the_downloaded_files()"
            },
            "keyword": "And "
          }
        ],
        "tags": [
          {
            "name": "@RegressionTest"
          }
        ]
      }
    ],
    "name": "Entering data to Grid Harmonization form - LEED v4.1 O+M: EB",
    "description": "",
    "id": "entering-data-to-grid-harmonization-form---leed-v4.1-o+m:-eb",
    "keyword": "Feature",
    "uri": "Include/features/ScoreCard/Grid Harmonization.feature",
    "tags": []
  }
]